Metadata-Version: 2.1
Name: motools
Version: 0.3
Summary: modelling tools
Home-page: UNKNOWN
License: UNKNOWN
Platform: UNKNOWN
